olleh.py
setup.py
olleh.egg-info/PKG-INFO
olleh.egg-info/SOURCES.txt
olleh.egg-info/dependency_links.txt
olleh.egg-info/entry_points.txt
olleh.egg-info/requires.txt
olleh.egg-info/top_level.txt