Metadata-Version: 1.0
Name: olleh
Version: 0.1.1
Summary: A command line tool to fetch usage data from olleh.com.
Home-page: UNKNOWN
Author: Choongmin Lee
Author-email: choongmin@me.com
License: UNKNOWN
Platform: UNKNOWN
